Workbook

Sheet Marketing Channels
A1: MARKETING CHANNEL ECONOMICS
A2: Cost Per Lead, Conversion Rates & Customer Acquisition Cost by Channel
A4: PAID ADVERTISING CHANNELS
A6: Channel | B6: Monthly Spend | C6: CPL | D6: Leads/Mo | E6: Lead→MQL % | F6: MQL→Cust % | G6: Customers | H6: CAC
A7: Google Ads - Search | B7: 3000 | C7: 85 | D7: =B7/C7 | E7: 0.25 | F7: 0.15 | G7: =D7*E7*F7 | H7: =B7/G7
A8: Google Ads - Display | B8: 1500 | C8: 25 | D8: =B8/C8 | E8: 0.08 | F8: 0.08 | G8: =D8*E8*F8 | H8: =B8/G8
A9: Facebook/Instagram Ads | B9: 2000 | C9: 35 | D9: =B9/C9 | E9: 0.12 | F9: 0.1 | G9: =D9*E9*F9 | H9: =B9/G9
A10: LinkedIn Ads | B10: 2500 | C10: 120 | D10: =B10/C10 | E10: 0.3 | F10: 0.2 | G10: =D10*E10*F10 | H10: =B10/G10
A11: YouTube Ads | B11: 1000 | C11: 20 | D11: =B11/C11 | E11: 0.05 | F11: 0.05 | G11: =D11*E11*F11 | H11: =B11/G11
A12: Bing Ads | B12: 500 | C12: 65 | D12: =B12/C12 | E12: 0.2 | F12: 0.12 | G12: =D12*E12*F12 | H12: =B12/G12
A13: Retargeting (all platforms) | B13: 1000 | C13: 15 | D13: =B13/C13 | E13: 0.35 | F13: 0.25 | G13: =D13*E13*F13 | H13: =B13/G13
A14: Construction Industry Sites | B14: 1500 | C14: 95 | D14: =B14/C14 | E14: 0.35 | F14: 0.18 | G14: =D14*E14*F14 | H14: =B14/G14
A15: PAID SUBTOTAL | B15: =SUM(B7:B14) | D15: =SUM(D7:D14) | G15: =SUM(G7:G14) | H15: =B15/G15
A18: ORGANIC / LOW-COST CHANNELS
A20: Channel | B20: Monthly Cost | C20: Est CPL | D20: Leads/Mo | E20: Lead→MQL % | F20: MQL→Cust % | G20: Customers | H20: CAC
A21: SEO / Content Marketing | B21: 500 | C21: 15 | D21: 35 | E21: 0.2 | F21: 0.12 | G21: =D21*E21*F21 | H21: =B21/G21
A22: Email Marketing | B22: 200 | C22: 5 | D22: 40 | E22: 0.15 | F22: 0.08 | G22: =D22*E22*F22 | H22: =B22/G22
A23: Referral Program | B23: 300 | C23: 25 | D23: 12 | E23: 0.5 | F23: 0.35 | G23: =D23*E23*F23 | H23: =B23/G23
A24: Social Media (organic) | B24: 150 | C24: 10 | D24: 15 | E24: 0.1 | F24: 0.06 | G24: =D24*E24*F24 | H24: =B24/G24
A25: Networking / Trade Shows | B25: 800 | C25: 150 | D25: 5 | E25: 0.6 | F25: 0.4 | G25: =D25*E25*F25 | H25: =B25/G25
A26: Partnerships / Co-marketing | B26: 400 | C26: 50 | D26: 8 | E26: 0.45 | F26: 0.3 | G26: =D26*E26*F26 | H26: =B26/G26
A27: Webinars / Education | B27: 300 | C27: 30 | D27: 10 | E27: 0.35 | F27: 0.2 | G27: =D27*E27*F27 | H27: =B27/G27
A28: Direct Outreach / Cold | B28: 200 | C28: 75 | D28: 3 | E28: 0.25 | F28: 0.15 | G28: =D28*E28*F28 | H28: =B28/G28
A29: GoHighLevel Automations | B29: 297 | C29: 20 | D29: 15 | E29: 0.3 | F29: 0.18 | G29: =D29*E29*F29 | H29: =B29/G29
A30: ORGANIC SUBTOTAL | B30: =SUM(B21:B29) | D30: =SUM(D21:D29) | G30: =SUM(G21:G29) | H30: =B30/G30
A32: TOTAL ALL CHANNELS | B32: =B15+B30 | D32: =D15+D30 | G32: =G15+G30 | H32: =B32/G32

Sheet CAC by Package
A1: CUSTOMER ACQUISITION COST BY PACKAGE
A2: Different packages have different CAC due to sales cycle complexity
A4: SALES CYCLE BY PACKAGE
A6: Metric | B6: A: Starter | C6: B: Pro | D6: C: Enterprise | E6: D: Platform
A7: Sales Cycle (days) | B7: 7 | C7: 30 | D7: 60 | E7: 90
A8: Touches to Close | B8: 3 | C8: 8 | D8: 15 | E8: 25
A9: Demo Required? | B9: No | C9: Yes (30 min) | D9: Yes (60 min) | E9: Yes (multi)
A10: Proposal Required? | B10: No | C10: Template | D10: Custom | E10: RFP Response
A11: Decision Makers | B11: 1 | C11: 1 | D11: 2 | E11: 3
A13: Marketing Spend Allocation | B13: 0.5 | C13: 0.25 | D13: 0.15 | E13: 0.1
A14: Monthly Marketing Budget | B14: ='Marketing Channels'!B32
A15: Allocated to Package | B15: =B13*B14 | C15: =C13*B14 | D15: =D13*B14 | E15: =E13*B14
A18: SALES LABOR COST PER CUSTOMER
A20: Metric | B20: A: Starter | C20: B: Pro | D20: C: Enterprise | E20: D: Platform
A21: Sales Hours per Customer | B21: 0.5 | C21: 3 | D21: 8 | E21: 20
A22: Sales Hourly Cost (loaded) | B22: 75 | C22: 75 | D22: 75 | E22: 75
A23: Sales Labor per Customer | B23: =B21*B22 | C23: =C21*C22 | D23: =D21*D22 | E23: =E21*E22
A25: Customers from Marketing | B25: 8 | C25: 3 | D25: 1.5 | E25: 0.5
A26: Marketing CAC (allocated) | B26: =B15/B25 | C26: =C15/C25 | D26: =D15/D25 | E26: =E15/E25
A28: TOTAL CAC | B28: =B23+B26 | C28: =C23+C26 | D28: =D23+D26 | E28: =E23+E26
A31: LTV:CAC ANALYSIS
A33: Metric | B33: A: Starter | C33: B: Pro | D33: C: Enterprise | E33: D: Platform
A34: Monthly Revenue | B34: 124 | C34: 3125 | D34: 12500 | E34: 37500
A35: Monthly Gross Profit | B35: 97 | C35: 2625 | D35: 10250 | E35: 28875
A36: Avg Customer Life (months) | B36: 12 | C36: 18 | D36: 24 | E36: 36
A37: Lifetime Value (LTV) | B37: =B35*B36 | C37: =C35*C36 | D37: =D35*D36 | E37: =E35*E36
A39: CAC (from above) | B39: =B28 | C39: =C28 | D39: =D28 | E39: =E28
A40: LTV:CAC Ratio | B40: =B37/B39 | C40: =C37/C39 | D40: =D37/D39 | E40: =E37/E39
A41: CAC Payback (months) | B41: =B39/B35 | C41: =C39/C35 | D41: =D39/D35 | E41: =E39/E35
A43: Target LTV:CAC | B43: 3:1 | C43: 3:1 | D43: 3:1 | E43: 3:1
A44: Status | B44: =IF(B40>=3,"✓ Good","⚠ Review") | C44: =IF(C40>=3,"✓ Good","⚠ Review") | D44: =IF(D40>=3,"✓ Good","⚠ Review") | E44: =IF(E40>=3,"✓ Good","⚠ Review")

Sheet True Profitability
A1: TRUE PROFITABILITY (INCLUDING ALL MARKETING)
A2: Unit economics with fully-loaded CAC
A4: MONTHLY UNIT ECONOMICS
A6: Metric | B6: A: Starter | C6: B: Pro | D6: C: Enterprise | E6: D: Platform
A7: Monthly Revenue | B7: 124 | C7: 3125 | D7: 12500 | E7: 37500
A9: Direct Costs:
A10: Infrastructure | B10: 8 | C10: 75 | D10: 250 | E10: 600
A11: Stripe (2.9%) | B11: =B7*0.029 | C11: =C7*0.029 | D11: =D7*0.029 | E11: =E7*0.029
A12: Labor/Support | B12: 5 | C12: 50 | D12: 200 | E12: 500
A13: Onboarding (amortized) | B13: 0 | C13: 42 | D13: 167 | E13: 833
A14: Total Direct Costs | B14: =SUM(B10:B13) | C14: =SUM(C10:C13) | D14: =SUM(D10:D13) | E14: =SUM(E10:E13)
A16: Gross Profit | B16: =B7-B14 | C16: =C7-C14 | D16: =D7-D14 | E16: =E7-E14
A17: Gross Margin % | B17: =B16/B7 | C17: =C16/C7 | D17: =D16/D7 | E17: =E16/E7
A19: CAC (amortized monthly):
A20: Total CAC | B20: ='CAC by Package'!B28 | C20: ='CAC by Package'!C28 | D20: ='CAC by Package'!D28 | E20: ='CAC by Package'!E28
A21: Customer Life (months) | B21: 12 | C21: 18 | D21: 24 | E21: 36
A22: Monthly CAC Amortization | B22: =B20/B21 | C22: =C20/C21 | D22: =D20/D21 | E22: =E20/E21
A24: Contribution Margin | B24: =B16-B22 | C24: =C16-C22 | D24: =D16-D22 | E24: =E16-E22
A25: Contribution Margin % | B25: =B24/B7 | C25: =C24/C7 | D25: =D24/D7 | E25: =E24/E7
A27: Allocated Overhead (10%) | B27: =B7*0.10 | C27: =C7*0.10 | D27: =D7*0.10 | E27: =E7*0.10
A29: TRUE NET PROFIT | B29: =B24-B27 | C29: =C24-C27 | D29: =D24-D27 | E29: =E24-E27
A30: TRUE NET MARGIN % | B30: =B29/B7 | C30: =C29/C7 | D30: =D29/D7 | E30: =E29/E7

Sheet Portfolio Economics
A1: BLENDED PORTFOLIO ECONOMICS
A2: Total business P&L including all marketing spend
A4: CUSTOMER MIX
B6: A: Starter | C6: B: Pro | D6: C: Enterprise | E6: D: Platform | F6: Total
A7: Active Customers | B7: 100 | C7: 30 | D7: 8 | E7: 2 | F7: =SUM(B7:E7)
A10: MONTHLY P&L
B12: A: Starter | C12: B: Pro | D12: C: Enterprise | E12: D: Platform | F12: Total
A13: Revenue | B13: =B7*124 | C13: =C7*3125 | D13: =D7*12500 | E13: =E7*37500 | F13: =SUM(B13:E13)
A15: Direct Costs | B15: =B7*17 | C15: =C7*258 | D15: =D7*980 | E15: =E7*3021 | F15: =SUM(B15:E15)
A16: Gross Profit | B16: =B13-B15 | C16: =C13-C15 | D16: =D13-D15 | E16: =E13-E15 | F16: =SUM(B16:E16)
A17: Gross Margin % | B17: =B16/B13 | C17: =C16/C13 | D17: =D16/D13 | E17: =E16/E13 | F17: =F16/F13
A19: MARKETING SPEND | F19: ='Marketing Channels'!B32
A20: New Customers this Month | B20: 8 | C20: 3 | D20: 1.5 | E20: 0.5 | F20: =SUM(B20:E20)
A22: Overhead (fixed) | F22: 14500
A24: OPERATING PROFIT | F24: =F16-F19-F22
A25: Operating Margin % | F25: =F24/F13
A27: Annual Revenue | F27: =F13*12
A28: Annual Marketing | F28: =F19*12
A29: Annual Operating Profit | F29: =F24*12
A32: KEY PERFORMANCE METRICS
A34: Blended CAC | B34: =F19/F20 | C34: Target: <$800
A35: Blended LTV | B35: =(B7*1164+C7*47250+D7*246000+E7*1039500)/F7
A36: LTV:CAC Ratio | B36: =B35/B34 | C36: Target: >3:1
A37: CAC Payback (months) | B37: =B34/(F16/F7) | C37: Target: <12 months
A38: Marketing as % of Revenue | B38: =F19/F13 | C38: Target: <15%
A39: Customer Acquisition Rate | B39: =F20 | C39: New customers/month
A40: Revenue per Customer | B40: =F13/F7
A41: Profit per Customer | B41: =F24/F7
