Workbook

Sheet Labor Rates
A1: KEALEE LABOR RATES & LOADED COSTS
A3: INTERNAL LABOR RATES
A5: Role | B5: Hourly Rate | C5: Burden % | D5: Loaded Rate | E5: Daily Cost | F5: Notes
A6: Tim (Owner/PM) | B6: 75 | C6: 0.3 | D6: =B6*(1+C6) | E6: =D6*8 | F6: Direct billable + oversight
A7: Senior Project Manager | B7: 55 | C7: 0.35 | D7: =B7*(1+C7) | E7: =D7*8 | F7: Future hire - manages 15-20 jobs
A8: Project Coordinator | B8: 35 | C8: 0.35 | D8: =B8*(1+C8) | E8: =D8*8 | F8: Future hire - admin support
A9: Estimator | B9: 50 | C9: 0.35 | D9: =B9*(1+C9) | E9: =D9*8 | F9: Takeoffs, bid prep
A10: Permit Expediter | B10: 30 | C10: 0.3 | D10: =B10*(1+C10) | E10: =D10*8 | F10: Permit running, inspections
A11: Field Superintendent | B11: 45 | C11: 0.35 | D11: =B11*(1+C11) | E11: =D11*8 | F11: Site visits, QC
A12: Admin/Bookkeeper | B12: 28 | C12: 0.3 | D12: =B12*(1+C12) | E12: =D12*8 | F12: Invoicing, AP/AR
A15: OVERHEAD & PROFIT (O&P) MARKUP
A17: Component | B17: Rate | C17: Applied To | D17: Notes
A18: General Overhead | B18: 0.15 | C18: All labor + direct costs | D18: Insurance, office, tools, vehicles
A19: Profit Margin | B19: 0.1 | C19: Subtotal after overhead | D19: Target net margin
A20: Combined O&P | B20: =B18+B19+(B18*B19) | C20: Effective markup | D20: Standard construction O&P
A23: BILLABLE RATE CALCULATION
A25: Role | B25: Loaded Cost | C25: O&P Markup | D25: Billable Rate | E25: Daily Bill Rate
A26: Tim (Owner/PM) | B26: =D6 | C26: =$B$20 | D26: =B26*(1+C26) | E26: =D26*8
A27: Senior PM | B27: =D7 | C27: =$B$20 | D27: =B27*(1+C27) | E27: =D27*8
A28: Project Coordinator | B28: =D8 | C28: =$B$20 | D28: =B28*(1+C28) | E28: =D28*8
A29: Estimator | B29: =D9 | C29: =$B$20 | D29: =B29*(1+C29) | E29: =D29*8
A30: Permit Expediter | B30: =D10 | C30: =$B$20 | D30: =B30*(1+C30) | E30: =D30*8
A31: Field Super | B31: =D11 | C31: =$B$20 | D31: =B31*(1+C31) | E31: =D31*8

Sheet Task Pricing
A1: TASK-BASED PRICING & TIME ESTIMATES
A3: A LA CARTE SERVICES (m-ops-services)
A5: Service | B5: Hours | C5: Role | D5: Labor Cost | E5: With O&P | F5: List Price | G5: Margin
A6: Site Visit & Inspection | B6: 2 | C6: Field Super | D6: =2*'Labor Rates'!D11 | E6: =D6*1.265 | F6: 125 | G6: =1-(D6/F6)
A7: Permit Application Prep | B7: 3 | C7: Permit Exp | D7: =3*'Labor Rates'!D10 | E7: =D7*1.265 | F7: 195 | G7: =1-(D7/F7)
A8: Code Compliance Review | B8: 2 | C8: Permit Exp | D8: =2*'Labor Rates'!D10 | E8: =D8*1.265 | F8: 150 | G8: =1-(D8/F8)
A9: Subcontractor Coordination | B9: 1.5 | C9: PM | D9: =1.5*'Labor Rates'!D6 | E9: =D9*1.265 | F9: 175 | G9: =1-(D9/F9)
A10: Daily Log & Photo Doc | B10: 0.5 | C10: Coordinator | D10: =0.5*'Labor Rates'!D8 | E10: =D10*1.265 | F10: 75 | G10: =1-(D10/F10)
A11: Change Order Processing | B11: 1 | C11: PM | D11: =1*'Labor Rates'!D6 | E11: =D11*1.265 | F11: 125 | G11: =1-(D11/F11)
A12: Pay App Preparation | B12: 2 | C12: PM | D12: =2*'Labor Rates'!D6 | E12: =D12*1.265 | F12: 250 | G12: =1-(D12/F12)
A13: Punch List Management | B13: 3 | C13: Coordinator | D13: =3*'Labor Rates'!D8 | E13: =D13*1.265 | F13: 195 | G13: =1-(D13/F13)
A14: RFI Response Coordination | B14: 1 | C14: PM | D14: =1*'Labor Rates'!D6 | E14: =D14*1.265 | F14: 125 | G14: =1-(D14/F14)
A15: Submittal Processing | B15: 1.5 | C15: Coordinator | D15: =1.5*'Labor Rates'!D8 | E15: =D15*1.265 | F15: 150 | G15: =1-(D15/F15)
A16: Safety Meeting Facilitation | B16: 1 | C16: Field Super | D16: =1*'Labor Rates'!D11 | E16: =D16*1.265 | F16: 125 | G16: =1-(D16/F16)
A19: ESTIMATION SERVICES
A21: Service | B21: Hours | C21: Role | D21: Labor Cost | E21: With O&P | F21: List Price | G21: Margin
A22: Basic Takeoff (<2,500 SF) | B22: 4 | C22: Estimator | D22: =4*'Labor Rates'!D9 | E22: =D22*1.265 | F22: 195 | G22: =1-(D22/F22)
A23: Standard Takeoff (2,500-5K SF) | B23: 8 | C23: Estimator | D23: =8*'Labor Rates'!D9 | E23: =D23*1.265 | F23: 495 | G23: =1-(D23/F23)
A24: Complex Takeoff (5K-10K SF) | B24: 16 | C24: Estimator | D24: =16*'Labor Rates'!D9 | E24: =D24*1.265 | F24: 995 | G24: =1-(D24/F24)
A25: Commercial Estimate (<25K SF) | B25: 24 | C25: Estimator | D25: =24*'Labor Rates'!D9 | E25: =D25*1.265 | F25: 1995 | G25: =1-(D25/F25)
A26: Large Commercial (25K-100K SF) | B26: 40 | C26: Estimator | D26: =40*'Labor Rates'!D9 | E26: =D26*1.265 | F26: 3495 | G26: =1-(D26/F26)
A27: Major Project (>100K SF) | B27: 80 | C27: Estimator | D27: =80*'Labor Rates'!D9 | E27: =D27*1.265 | F27: 5995 | G27: =1-(D27/F27)
A28: Bid Package Assembly | B28: 6 | C28: PM | D28: =6*'Labor Rates'!D6 | E28: =D28*1.265 | F28: 695 | G28: =1-(D28/F28)

Sheet 100 Jobs Model
A1: HOW 100 JOBS AT $16,500/MO WORKS
A2: Package C: Enterprise PM Package - Unit Economics Breakdown
A4: MONTHLY REVENUE
A6: Package C Monthly Fee | B6: 16500 | E6: Fixed monthly subscription
A7: Jobs Included | B7: 100 | E7: Active projects under management
A8: Revenue per Job | B8: =B6/B7 | E8: Effective rate per project
A11: TIME ALLOCATION PER JOB (MONTHLY)
A13: Activity | B13: Hrs/Job/Mo | C13: Role | D13: Cost/Job | E13: Notes
A14: Schedule review & update | B14: 0.25 | C14: PM | D14: =B14*'Labor Rates'!D6 | E14: Weekly 15-min check
A15: Daily log review (automated) | B15: 0.1 | C15: Coordinator | D15: =B15*'Labor Rates'!D8 | E15: AI-assisted, exception-based
A16: Owner communication | B16: 0.25 | C16: PM | D16: =B16*'Labor Rates'!D6 | E16: Weekly status update
A17: Sub coordination | B17: 0.2 | C17: Coordinator | D17: =B17*'Labor Rates'!D8 | E17: Scheduling, follow-up
A18: Financial tracking | B18: 0.15 | C18: PM | D18: =B18*'Labor Rates'!D6 | E18: Budget monitoring
A19: Issue resolution | B19: 0.25 | C19: PM | D19: =B19*'Labor Rates'!D6 | E19: Problem-solving as needed
A20: Document management | B20: 0.1 | C20: Coordinator | D20: =B20*'Labor Rates'!D8 | E20: Filing, distribution
A21: Quality checks | B21: 0.15 | C21: Field Super | D21: =B21*'Labor Rates'!D11 | E21: Spot inspections
A22: Platform overhead | B22: 0.05 | C22: Admin | D22: =B22*'Labor Rates'!D12 | E22: System maintenance
A24: TOTAL HOURS PER JOB/MONTH | B24: =SUM(B14:B22)
A25: TOTAL LABOR COST PER JOB/MONTH | D25: =SUM(D14:D22)
A28: MONTHLY P&L FOR 100 JOBS
A30: Monthly Revenue | B30: =B6
A32: Direct Labor (100 jobs × cost/job) | B32: =D25*100
A33: Platform Infrastructure | B33: 250 | E33: Hosting, DB, APIs
A34: Stripe Fees (2.9% + $0.30) | B34: =B30*0.029+0.30
A35: Total Direct Costs | B35: =SUM(B32:B34)
A37: Gross Profit | B37: =B30-B35
A38: Gross Margin % | B38: =B37/B30
A40: Allocated Overhead (15%) | B40: =B30*0.15 | E40: Insurance, office, tools
A41: Net Profit Before Labor | B41: =B37-B40
A42: Net Margin % | B42: =B41/B30
A45: STAFFING REQUIREMENT
A47: Total Hours for 100 Jobs/Month | B47: =B24*100 | C47: hours
A48: Working Hours/Person/Month | B48: 160 | C48: hours (40hr × 4wk)
A49: FTEs Required | B49: =B47/B48 | C49: full-time equivalents
A51: Recommended Staffing:
A52: - Senior PM (manages 30-40 jobs) | B52: 2 | C52: people
A53: - Project Coordinator | B53: 1 | C53: person
A54: - Field Super (part-time) | B54: 0.25 | C54: FTE

Sheet Daily Economics
A1: REAL-TIME DAILY ECONOMICS
A2: Daily P&L by Package Tier (22 working days/month)
A4: DAILY REVENUE
A6: Metric | B6: A: Starter | C6: B: Pro | D6: C: Enterprise | E6: D: Platform | F6: Total | G6: Notes
A7: Active Customers | B7: 100 | C7: 30 | D7: 8 | E7: 2 | F7: =SUM(B7:E7)
A8: Monthly Price (avg) | B8: 124 | C8: 3125 | D8: 12500 | E8: 37500
A9: Monthly Revenue | B9: =B7*B8 | C9: =C7*C8 | D9: =D7*D8 | E9: =E7*E8 | F9: =SUM(B9:E9)
A10: DAILY REVENUE (÷22 days) | B10: =B9/22 | C10: =C9/22 | D10: =D9/22 | E10: =E9/22 | F10: =SUM(B10:E10)
A13: DAILY COSTS
A15: Metric | B15: A: Starter | C15: B: Pro | D15: C: Enterprise | E15: D: Platform | F15: Total | G15: Notes
A16: Hrs/Customer/Day | B16: 0.02 | C16: 0.1 | D16: 0.07 | E16: 0.2 | G16: Based on service level
A17: Total Daily Hours | B17: =B7*B16 | C17: =C7*C16 | D17: =D7*D16 | E17: =E7*E16 | F17: =SUM(B17:E17)
A18: Blended Hourly Cost | B18: 47 | C18: 74 | D18: 68 | E18: 85 | G18: Loaded cost by tier
A19: Daily Labor Cost | B19: =B17*B18 | C19: =C17*C18 | D19: =D17*D18 | E19: =E17*E18 | F19: =SUM(B19:E19)
A20: Daily Infrastructure | B20: =100*8/30 | C20: =30*75/30 | D20: =8*250/30 | E20: =2*600/30 | F20: =SUM(B20:E20)
A21: Daily Stripe Fees | B21: =B10*0.029 | C21: =C10*0.029 | D21: =D10*0.029 | E21: =E10*0.029 | F21: =SUM(B21:E21)
A22: TOTAL DAILY COST | B22: =SUM(B19:B21) | C22: =SUM(C19:C21) | D22: =SUM(D19:D21) | E22: =SUM(E19:E21) | F22: =SUM(B22:E22)
A25: DAILY PROFIT
A27: Metric | B27: A: Starter | C27: B: Pro | D27: C: Enterprise | E27: D: Platform | F27: Total | G27: Notes
A28: Daily Gross Profit | B28: =B10-B22 | C28: =C10-C22 | D28: =D10-D22 | E28: =E10-E22 | F28: =SUM(B28:E28)
A29: Daily Gross Margin % | B29: =B28/B10 | C29: =C28/C10 | D29: =D28/D10 | E29: =E28/E10 | F29: =F28/F10
A31: Daily Fixed Overhead | F31: 660 | G31: Tim + base costs
A32: DAILY NET PROFIT | F32: =F28-F31
A33: Daily Net Margin % | F33: =F32/F10
A36: REAL-TIME OPERATIONAL METRICS
A38: Revenue per Hour Worked | F38: =F10/F17 | G38: Target: >$500/hr
A39: Profit per Hour Worked | F39: =F32/F17 | G39: Target: >$150/hr
A40: Customers per FTE (8hr day) | F40: =F7/(F17/8)
A41: Break-even Customers (daily) | F41: =F31/(F10/F7) | G41: Min customers to cover fixed
