Workbook

Sheet Unit Economics
A1: KEALEE PLATFORM - PROFIT MARGIN ANALYSIS
A2: Unit Economics by Package Tier
A4: Metric | B4: A: Starter | C4: B: Professional | D4: C: Enterprise | E4: D: Platform | F4: Notes
A5: Monthly Price (Low) | B5: 49 | C5: 1750 | D5: 8500 | E5: 25000 | F5: Blue = editable inputs
A6: Monthly Price (High) | B6: 199 | C6: 4500 | D6: 16500 | E6: 50000
A7: Avg Monthly Revenue | B7: =(B5+B6)/2 | C7: =(C5+C6)/2 | D7: =(D5+D6)/2 | E7: =(E5+E6)/2 | F7: Midpoint
A9: DIRECT COSTS
A10: Infrastructure (hosting/db) | B10: 8 | C10: 75 | D10: 250 | E10: 600 | F10: Vercel + Railway + Supabase
A11: Stripe Processing (2.9% + $0.30) | B11: =B7*0.029+0.30 | C11: =C7*0.029+0.30 | D11: =D7*0.029+0.30 | E11: =E7*0.029+0.30 | F11: 2.9% + $0.30/txn
A12: Support Cost Allocation | B12: 5 | C12: 50 | D12: 200 | E12: 500 | F12: Based on support tier
A13: Onboarding (amortized/12mo) | B13: 0 | C13: 42 | D13: 167 | E13: 833 | F13: Setup cost / 12 months
A14: Total Direct Costs | B14: =SUM(B10:B13) | C14: =SUM(C10:C13) | D14: =SUM(D10:D13) | E14: =SUM(E10:E13)
A16: GROSS MARGIN
A17: Gross Profit ($) | B17: =B7-B14 | C17: =C7-C14 | D17: =D7-D14 | E17: =E7-E14
A18: Gross Margin (%) | B18: =B17/B7 | C18: =C17/C7 | D18: =D17/D7 | E18: =E17/E7 | F18: Target: 75-85%
A20: ALLOCATED OVERHEAD
A21: Platform Dev (% of revenue) | B21: 0.15 | C21: 0.12 | D21: 0.1 | E21: 0.08 | F21: Decreases with scale
A22: Sales & Marketing (% of rev) | B22: 0.25 | C22: 0.2 | D22: 0.15 | E22: 0.1 | F22: CAC amortized
A23: G&A Allocation (% of rev) | B23: 0.1 | C23: 0.08 | D23: 0.06 | E23: 0.05 | F23: Admin overhead
A24: Total Overhead (%) | B24: =SUM(B21:B23) | C24: =SUM(C21:C23) | D24: =SUM(D21:D23) | E24: =SUM(E21:E23)
A25: Total Overhead ($) | B25: =B24*B7 | C25: =C24*C7 | D25: =D24*D7 | E25: =E24*E7
A27: NET MARGIN
A28: Operating Profit ($) | B28: =B17-B25 | C28: =C17-C25 | D28: =D17-D25 | E28: =E17-E25
A29: Operating Margin (%) | B29: =B28/B7 | C29: =C28/C7 | D29: =D28/D7 | E29: =E28/E7 | F29: Target: 20-35%
A31: ANNUAL VIEW
A32: Annual Revenue | B32: =B7*12 | C32: =C7*12 | D32: =D7*12 | E32: =E7*12
A33: Annual Gross Profit | B33: =B17*12 | C33: =C17*12 | D33: =D17*12 | E33: =E17*12
A34: Annual Operating Profit | B34: =B28*12 | C34: =C28*12 | D34: =D28*12 | E34: =E28*12
A35: LTV (24-mo avg life) | B35: =B28*24 | C35: =C28*24 | D35: =D28*24 | E35: =E28*24 | F35: Assumes 24-month retention

Sheet Scenario Analysis
A1: REVENUE SCENARIO ANALYSIS
A3: Customer Mix Scenarios
A5: Scenario | B5: Conservative | C5: Base Case | D5: Aggressive
A6: Package A Customers | B6: 50 | C6: 100 | D6: 200
A7: Package B Customers | B7: 15 | C7: 30 | D7: 60
A8: Package C Customers | B8: 3 | C8: 8 | D8: 15
A9: Package D Customers | B9: 0 | C9: 2 | D9: 5
A11: Package A Monthly Rev | B11: =B6*124 | C11: =C6*124 | D11: =D6*124
A12: Package B Monthly Rev | B12: =B7*3125 | C12: =C7*3125 | D12: =D7*3125
A13: Package C Monthly Rev | B13: =B8*12500 | C13: =C8*12500 | D13: =D8*12500
A14: Package D Monthly Rev | B14: =B9*37500 | C14: =C9*37500 | D14: =D9*37500
A15: Total Monthly Revenue | B15: =SUM(B11:B14) | C15: =SUM(C11:C14) | D15: =SUM(D11:D14)
A17: Blended Gross Margin | B17: 0.82 | C17: 0.84 | D17: 0.85
A18: Monthly Gross Profit | B18: =B15*B17 | C18: =C15*C17 | D18: =D15*D17
A20: Total Overhead ($) | B20: 25000 | C20: 45000 | D20: 75000
A21: Monthly Operating Profit | B21: =B18-B20 | C21: =C18-C20 | D21: =D18-D20
A22: Operating Margin | B22: =B21/B15 | C22: =C21/C15 | D22: =D21/D15
A24: Annual Revenue | B24: =B15*12 | C24: =C15*12 | D24: =D15*12
A25: Annual Operating Profit | B25: =B21*12 | C25: =C21*12 | D25: =D21*12

Sheet Break-Even
A1: BREAK-EVEN ANALYSIS
A3: Fixed Monthly Costs
A5: Tim (Founder/CEO) | B5: 10000
A6: Platform Infrastructure (base) | B6: 500
A7: Software/Tools | B7: 500
A8: Insurance/Legal/Accounting | B8: 1500
A9: Marketing (base) | B9: 2000
A10: Total Fixed Costs | B10: =SUM(B5:B9)
A12: Customers Needed to Break Even
A14: Package | B14: Avg Price | C14: Gross Margin | D14: Contrib/Customer | E14: Customers Needed
A15: A: Starter | B15: 124 | C15: 0.78 | D15: =B15*C15 | E15: =CEILING($B$10/D15,1)
A16: B: Professional | B16: 3125 | C16: 0.84 | D16: =B16*C16 | E16: =CEILING($B$10/D16,1)
A17: C: Enterprise | B17: 12500 | C17: 0.82 | D17: =B17*C17 | E17: =CEILING($B$10/D17,1)
A18: D: Platform | B18: 37500 | C18: 0.77 | D18: =B18*C18 | E18: =CEILING($B$10/D18,1)
A20: Interpretation: You need ~5 Package B customers OR ~2 Package C customers to cover fixed costs

Sheet Summary
A1: PROFIT MARGIN SUMMARY
A3: Key Metrics by Package
B5: A: Starter | C5: B: Pro | D5: C: Enterprise | E5: D: Platform
A6: Avg Monthly Price | B6: ='Unit Economics'!B7 | C6: ='Unit Economics'!C7 | D6: ='Unit Economics'!D7 | E6: ='Unit Economics'!E7
A7: Gross Margin % | B7: ='Unit Economics'!B18 | C7: ='Unit Economics'!C18 | D7: ='Unit Economics'!D18 | E7: ='Unit Economics'!E18
A8: Operating Margin % | B8: ='Unit Economics'!B29 | C8: ='Unit Economics'!C29 | D8: ='Unit Economics'!D29 | E8: ='Unit Economics'!E29
A9: Monthly Op. Profit | B9: ='Unit Economics'!B28 | C9: ='Unit Economics'!C28 | D9: ='Unit Economics'!D28 | E9: ='Unit Economics'!E28
A10: Annual Op. Profit | B10: ='Unit Economics'!B34 | C10: ='Unit Economics'!C34 | D10: ='Unit Economics'!D34 | E10: ='Unit Economics'!E34
A11: 24-mo LTV | B11: ='Unit Economics'!B35 | C11: ='Unit Economics'!C35 | D11: ='Unit Economics'!D35 | E11: ='Unit Economics'!E35
A14: KEY INSIGHTS
A16: • Package B (Professional) offers best margin-to-volume balance
A17: • Package C (Enterprise) highest absolute profit per customer
A18: • Package A primarily serves as funnel entry / lead qualification
A19: • Package D requires careful scoping to maintain margins
A20: • Target blended gross margin: 80-85%
A21: • Target operating margin: 25-35%
